LICENSE
MANIFEST.in
README
setup.py
DataPipeline/Base.py
DataPipeline/CHANGES.txt
DataPipeline/Custom.py
DataPipeline/Data.py
DataPipeline/Dialogs.py
DataPipeline/Editor.py
DataPipeline/Helper.py
DataPipeline/Images.py
DataPipeline/Importer.py
DataPipeline/PipelineApp.py
DataPipeline/PipelineCommand.py
DataPipeline/Processing.py
DataPipeline/ProgressBar.py
DataPipeline/Rename.py
DataPipeline/Testing.py
DataPipeline/Unittests.py
DataPipeline/Utilities.py
DataPipeline/Wt_IP20_KPO4.txt
DataPipeline/__init__.py
DataPipeline/app.ico
DataPipeline/logo.png
DataPipeline/modeldesign.ico
DataPipeline.egg-info/PKG-INFO
DataPipeline.egg-info/SOURCES.txt
DataPipeline.egg-info/dependency_links.txt
DataPipeline.egg-info/entry_points.txt
DataPipeline.egg-info/requires.txt
DataPipeline.egg-info/top_level.txt
DataPipeline/samples/J-810_cd.txt
DataPipeline/testfiles/databycol1.txt
DataPipeline/testfiles/databycol2.txt
DataPipeline/testfiles/databycol_grouped.txt
DataPipeline/testfiles/databycol_paired.txt
DataPipeline/testfiles/databycol_paired_double.txt
DataPipeline/testfiles/databyrow1.txt
DataPipeline/testfiles/databyrow2.txt
DataPipeline/testfiles/databyrow_errors.txt
DataPipeline/testfiles/databyrow_grouped.txt
DataPipeline/testfiles/databyrow_paired.txt
DataPipeline/testfiles/databyrow_paired_double.txt
DataPipeline/testfiles/NMRdata/10.txt.inp
DataPipeline/testfiles/NMRdata/100.txt.inp
DataPipeline/testfiles/NMRdata/101.txt.inp
DataPipeline/testfiles/NMRdata/102.txt.inp
DataPipeline/testfiles/NMRdata/103.txt.inp
DataPipeline/testfiles/NMRdata/104.txt.inp
DataPipeline/testfiles/NMRdata/105.txt.inp
DataPipeline/testfiles/NMRdata/11.txt.inp
DataPipeline/testfiles/NMRdata/12.txt.inp
DataPipeline/testfiles/NMRdata/13.txt.inp
DataPipeline/testfiles/NMRdata/14.txt.inp
DataPipeline/testfiles/NMRdata/15.txt.inp
DataPipeline/testfiles/NMRdata/16.txt.inp
DataPipeline/testfiles/NMRdata/17.txt.inp
DataPipeline/testfiles/NMRdata/19.txt.inp
DataPipeline/testfiles/NMRdata/2.txt.inp
DataPipeline/testfiles/NMRdata/20.txt.inp
DataPipeline/testfiles/NMRdata/21.txt.inp
DataPipeline/testfiles/NMRdata/22.txt.inp
DataPipeline/testfiles/NMRdata/23.txt.inp
DataPipeline/testfiles/NMRdata/24.txt.inp
