Metadata-Version: 1.0
Name: DataPipeline
Version: 1.2
Summary: DataPipeline Tool
Home-page: http://pypi.python.org/packages/source/D/DataPipeline/
Author: Damien Farrell
Author-email: farrell.damien[at]gmail.com
License: GPL v3
Platform: UNKNOWN
